AUTHORS
LICENSE
MANIFEST.in
README.rst
VERSION
requirements.txt
setup.py
src/ldp_archive_mirror/__init__.py
src/ldp_archive_mirror/api.py
src/ldp_archive_mirror/cli.py
src/ldp_archive_mirror/db.py
src/ldp_archive_mirror/exceptions.py
src/ldp_archive_mirror/fs.py
src/ldp_archive_mirror/ldp_mirror.py
src/ldp_archive_mirror/log.py
src/ldp_archive_mirror/pca.py
src/ldp_archive_mirror/pgp.py
src/ldp_archive_mirror.egg-info/PKG-INFO
src/ldp_archive_mirror.egg-info/SOURCES.txt
src/ldp_archive_mirror.egg-info/dependency_links.txt
src/ldp_archive_mirror.egg-info/entry_points.txt
src/ldp_archive_mirror.egg-info/requires.txt
src/ldp_archive_mirror.egg-info/top_level.txt
src/ldp_archive_mirror.egg-info/zip-safe