Metadata-Version: 2.1
Name: ldp-archive-mirror
Version: 0.2.0
Summary: This tools allows you to get a local copy of all your cold stored archives on Logs Data Platform.
Home-page: https://github.com/ovh/ldp-archive-mirror
Author: OVH Group
Author-email: opensource@ovh.net
License: OVH SAS
Keywords: LDP OVH
Classifier: Programming Language :: Python
License-File: LICENSE
License-File: AUTHORS
